jhc_cf_sdk_test/__init__.py
jhc_cf_sdk_test/api_client.py
jhc_cf_sdk_test/configuration.py
jhc_cf_sdk_test/exceptions.py
jhc_cf_sdk_test/rest.py
jhc_cf_sdk_test/schemas.py
jhc_cf_sdk_test/apis/__init__.py
jhc_cf_sdk_test/apis/path_to_api.py
jhc_cf_sdk_test/apis/tag_to_api.py
jhc_cf_sdk_test/apis/paths/__init__.py
jhc_cf_sdk_test/apis/paths/api_v1_access_rules.py
jhc_cf_sdk_test/apis/paths/api_v1_access_rules_lookup.py
jhc_cf_sdk_test/apis/paths/api_v1_access_rules_rule_id.py
jhc_cf_sdk_test/apis/paths/api_v1_access_rules_rule_id_approvers.py
jhc_cf_sdk_test/apis/paths/api_v1_admin_access_rules.py
jhc_cf_sdk_test/apis/paths/api_v1_admin_access_rules_rule_id.py
jhc_cf_sdk_test/apis/paths/api_v1_admin_access_rules_rule_id_archive.py
jhc_cf_sdk_test/apis/paths/api_v1_admin_access_rules_rule_id_versions.py
jhc_cf_sdk_test/apis/paths/api_v1_admin_access_rules_rule_id_versions_version.py
jhc_cf_sdk_test/apis/paths/api_v1_admin_deployment_version.py
jhc_cf_sdk_test/apis/paths/api_v1_admin_groups.py
jhc_cf_sdk_test/apis/paths/api_v1_admin_groups_group_id.py
jhc_cf_sdk_test/apis/paths/api_v1_admin_identity.py
jhc_cf_sdk_test/apis/paths/api_v1_admin_identity_sync.py
jhc_cf_sdk_test/apis/paths/api_v1_admin_providers.py
jhc_cf_sdk_test/apis/paths/api_v1_admin_providers_provider_id.py
jhc_cf_sdk_test/apis/paths/api_v1_admin_providers_provider_id_args.py
jhc_cf_sdk_test/apis/paths/api_v1_admin_providers_provider_id_args_arg_id_options.py
jhc_cf_sdk_test/apis/paths/api_v1_admin_providersetups.py
jhc_cf_sdk_test/apis/paths/api_v1_admin_providersetups_providersetup_id.py
jhc_cf_sdk_test/apis/paths/api_v1_admin_providersetups_providersetup_id_complete.py
jhc_cf_sdk_test/apis/paths/api_v1_admin_providersetups_providersetup_id_instructions.py
jhc_cf_sdk_test/apis/paths/api_v1_admin_providersetups_providersetup_id_steps_step_index_complete.py
jhc_cf_sdk_test/apis/paths/api_v1_admin_providersetups_providersetup_id_validate.py
jhc_cf_sdk_test/apis/paths/api_v1_admin_requests.py
jhc_cf_sdk_test-1.2.5.dist-info/LICENCE
jhc_cf_sdk_test-1.2.5.dist-info/METADATA
jhc_cf_sdk_test-1.2.5.dist-info/WHEEL
jhc_cf_sdk_test-1.2.5.dist-info/top_level.txt
jhc_cf_sdk_test-1.2.5.dist-info/RECORD
