Metadata-Version: 2.1
Name: jhc-cf-sdk-test
Version: 1.2.5
Summary: Common Fate
Home-page: 
Author: Common Fate
Author-email: team@openapitools.org
Keywords: OpenAPI,OpenAPI-Generator,Common Fate
Requires-Python: >=3.7
License-File: LICENCE
Requires-Dist: certifi (>=14.5.14)
Requires-Dist: frozendict (~=2.3.4)
Requires-Dist: python-dateutil (~=2.7.0)
Requires-Dist: setuptools (>=21.0.0)
Requires-Dist: typing-extensions (~=4.3.0)
Requires-Dist: urllib3 (~=1.26.7)
